chessengine/__init__.py
chessengine/__main__.py
chessengine/bitboard.py
chessengine/cli.py
chessengine/exceptions.py
chessengine/lookup_tables.py
chessengine/moves.py
chessengine/play.py
chessengine/utils.py
chessengine/openings/Modern.pgn
chessengine/openings/__init__.py
chessengine/pgn/__init__.py
chessengine/pgn/node.py
chessengine/pgn/parser.py
chessengine/pgn/utils.py
chessengine-0.3.4.dist-info/LICENSE
chessengine-0.3.4.dist-info/METADATA
chessengine-0.3.4.dist-info/WHEEL
chessengine-0.3.4.dist-info/entry_points.txt
chessengine-0.3.4.dist-info/top_level.txt
chessengine-0.3.4.dist-info/RECORD
