Metadata-Version: 2.1
Name: chessengine
Version: 0.3.4
Summary: A chess engine with no dependencies
Author-email: Hrushikesh Vaidya <hrushikeshrv@gmail.com>
License: MIT License
Project-URL: Homepage, https://github.com/hrushikeshrv/chessengine
Project-URL: Bug Tracker, https://github.com/hrushikeshrv/chessengine/issues
Classifier: Programming Language :: Python :: 3
Classifier: License :: OSI Approved :: MIT License
Classifier: Operating System :: OS Independent
Requires-Python: >3.5
License-File: LICENSE
